market/FinancialMarketData.py
market/QuestradeData.py
market/__init__.py
marketData-0.2.0.dist-info/LICENSE
marketData-0.2.0.dist-info/METADATA
marketData-0.2.0.dist-info/WHEEL
marketData-0.2.0.dist-info/top_level.txt
marketData-0.2.0.dist-info/RECORD
