Metadata-Version: 2.1
Name: marketData
Version: 0.2.0
Summary: This module is to retrieve market data
Home-page: https://github.com/bhajian/market-data
Author: Behnam Hajian
Author-email: bhajian@gmail.com
License: MIT
Platform: UNKNOWN
Classifier: Programming Language :: Python :: 3
Classifier: License :: OSI Approved :: MIT License
Classifier: Operating System :: OS Independent
Requires-Python: >=3.6
